<?xml version="1.0" encoding="utf-8"?>
<squadre>
<squadra>
  <nome>ciofeca</nome>
  <img>ciofeca.jpg</img>
  <storico>
    <campionato>
      <stagione>2000/01</stagione>
      <posizione>8</posizione>
      <vecchio_nome>C. Potemkin</vecchio_nome>
    </campionato>
    <campionato>
      <stagione>2001/02</stagione>
      <posizione>6</posizione>
      <vecchio_nome>C. Potemkin</vecchio_nome>
    </campionato>
    <campionato>
      <stagione>2002/03</stagione>
      <posizione>2</posizione>
      <vecchio_nome>Gli Struzzi</vecchio_nome>
    </campionato>
    <campionato>
      <stagione>2003/04</stagione>
      <posizione>4</posizione>
    </campionato>
    <campionato>
      <stagione>2004/05</stagione>
      <posizione>1</posizione>
    </campionato>
    <campionato>
      <stagione>2005/06</stagione>
      <posizione>1</posizione>
      <supercoppa>SC</supercoppa>
    </campionato>
    <campionato>
      <stagione>2006/07</stagione>
      <posizione>1</posizione>
    </campionato>
    <campionato>
      <stagione>2007/08</stagione>
      <posizione>7</posizione>
      <coppa>C</coppa>
      <supercoppa>SC</supercoppa>
    </campionato>
    <campionato>
      <stagione>2008/09</stagione>
      <posizione>3</posizione>
    </campionato>
    <campionato>
      <stagione>2009/10</stagione>
      <posizione>2</posizione>
    </campionato>	
	  <campionato>
      <stagione>2010/11</stagione>
      <posizione>4</posizione>
    </campionato>
    <campionato>
      <stagione>2011/12</stagione>
      <posizione>1</posizione>
    </campionato>
    <campionato>
      <stagione>2012/13</stagione>
      <posizione>1</posizione>
    </campionato>
	<campionato>
      <stagione>2013/14</stagione>
      <posizione>1</posizione>
	  <supercoppa>SC</supercoppa>
    </campionato>
  </storico>
</squadra>
</squadre>
